[{"_id":"6312311dc355144b72eda985","photoUrl":"http://placehold.it/32x32","name":"Warner Quinn","gender":"male","email":"warnerquinn@ontagene.com","phone":"+1 (847) 509-3029","address":"458 Turnbull Avenue, Chase, Federated States Of Micronesia, 2693"},{"_id":"6312311d6adb310e86048b0c","photoUrl":"http://placehold.it/32x32","name":"Saundra Villarreal","gender":"female","email":"saundravillarreal@ontagene.com","phone":"+1 (925) 518-2105","address":"937 Rockwell Place, Corriganville, Colorado, 1048"},{"_id":"6312311d6546bfe077aade5e","photoUrl":"http://placehold.it/32x32","name":"Sylvia Humphrey","gender":"female","email":"sylviahumphrey@ontagene.com","phone":"+1 (906) 439-2150","address":"119 Harbor Court, Tivoli, New Hampshire, 8022"},{"_id":"6312311df389babfbff088ed","photoUrl":"http://placehold.it/32x32","name":"Silvia Lambert","gender":"female","email":"silvialambert@ontagene.com","phone":"+1 (930) 550-2397","address":"537 Amber Street, Carlton, New Jersey, 9509"},{"_id":"6312311dca0811ef47546796","photoUrl":"http://placehold.it/32x32","name":"Emilia Carver","gender":"female","email":"emiliacarver@ontagene.com","phone":"+1 (813) 403-2675","address":"269 Coyle Street, Keyport, Nebraska, 2814"},{"_id":"6312311d61b9d590c29f3d54","photoUrl":"http://placehold.it/32x32","name":"Claudette Serrano","gender":"female","email":"claudetteserrano@ontagene.com","phone":"+1 (929) 498-3062","address":"731 Applegate Court, Fairlee, Alabama, 3076"},{"_id":"6312311d38e7f94ee75a6d5e","photoUrl":"http://placehold.it/32x32","name":"rafia","gender":"female","email":"carmelavasquez@ontagene.com","phone":"+1 (880) 515-3565","address":"700 Fillmore Place, Dalton, Tennessee, 4600"},{"_id":"6312311d38e7f94ee75a6d5ef","photoUrl":"http://placehold.it/32x32","name":"Carmel","gender":"female","email":"carmelavasquez@ontagene.com","phone":"+1 (880) 515-3565","address":"700 Fillmore Place, Dalton, Tennessee, 4600"},{"_id":"6312311d38e7f94ee75a6d5effff","photoUrl":"http://placehold.it/32x32","name":"riedoy","gender":"feale","email":"carmelavasquez@ontagene.com","phone":"+1 (880) 515-3565","address":"700 Fillmore Place, Dalton, Tennessee, 4600"},{"_id":"6312311d38e7f94ee75a6d5e","photoUrl":"http://placehold.it/32x32","name":"rafia","gender":"female","email":"carmelavasquez@ontagene.com","phone":"+1 (880) 515-3565","address":"700 Fillmore Place, Dalton, Tennessee, 4600"}]